asyncthreads
