Metadata-Version: 1.1
Name: asyncthreads
Version: 1.5.4
Summary: asyncthreads: asynchronous thread utility objects
Home-page: http://bitbucket.org/agillis/asyncthreads
Author: Andrew Gillis
Author-email: gillis.andrewj@gmail.com
License: http://www.opensource.org/licenses/mit-license.php
Keywords: threads threadpool reactor
Platform: unix
Platform: linux
Platform: osx
Platform: cygwin
Platform: win32
Classifier: Development Status :: 5 - Production/Stable
Classifier: Intended Audience :: Developers
Classifier: License :: OSI Approved :: MIT License
Classifier: Operating System :: POSIX
Classifier: Operating System :: Microsoft :: Windows
Classifier: Operating System :: MacOS :: MacOS X
Classifier: Topic :: Software Development :: Libraries
Classifier: Topic :: Utilities
Classifier: Programming Language :: Python
Classifier: Programming Language :: Python :: 2.7
Classifier: Programming Language :: Python :: 3
